swarm_star/__init__.py
swarm_star/actions/__init__.py
swarm_star/actions/action_space.json
swarm_star/actions/communication/ask_user_questions.py
swarm_star/actions/reasoning/__init__.py
swarm_star/actions/reasoning/decompose_directive.py
swarm_star/actions/reasoning/route_goal.py
swarm_star/memory/__init__.py
swarm_star/memory/memory_space_metadata.json
swarm_star/memory/swarm/__init__.py
swarm_star/memory/swarm/documentation/__init__.py
swarm_star/memory/swarm/documentation/configuration_chatbot.md
swarm_star/metadata/action_space.bson
swarm_star/metadata/action_space.metadata.json
swarm_star/swarm/__init__.py
swarm_star/swarm/core.py
swarm_star/swarm/setup.py
swarm_star/swarm/types/__init__.py
swarm_star/swarm/types/action_metadata.py
swarm_star/swarm/types/memory_metadata.py
swarm_star/swarm/types/swarm.py
swarm_star/swarm/types/swarm_config.py
swarm_star/swarm/types/swarm_history.py
swarm_star/swarm/types/swarm_state.py
swarm_star/swarm/types/util_metadata.py
swarm_star/utils/__init__.py
swarm_star/utils/action_utils/__init__.py
swarm_star/utils/action_utils/execute_action/__init__.py
swarm_star/utils/action_utils/execute_action/internal_python_main.py
swarm_star/utils/action_utils/execute_action/main.py
swarm_star/utils/action_utils/execute_blocking_operation/__init__.py
swarm_star/utils/action_utils/execute_blocking_operation/internal_action.py
swarm_star/utils/action_utils/execute_blocking_operation/main.py
swarm_star/utils/action_utils/execute_blocking_operation/openai_instructor_completion.py
swarm_star/utils/ai/openai_instructor.py
swarm_star/utils/data/__init__.py
swarm_star/utils/data/file_operations/__init__.py
swarm_star/utils/data/file_operations/azure_blob_storage.py
swarm_star/utils/data/file_operations/local_storage.py
swarm_star/utils/data/file_operations/main.py
swarm_star/utils/data/folder_operations/__init__.py
swarm_star/utils/data/folder_operations/azure_blob_storage.py
swarm_star/utils/data/folder_operations/local_storage.py
swarm_star-0.1.0.dist-info/LICENSE
swarm_star-0.1.0.dist-info/METADATA
swarm_star-0.1.0.dist-info/WHEEL
swarm_star-0.1.0.dist-info/RECORD
